<Properties StartupConfiguration="{DE186BBC-C571-4111-943F-7B9826562B63}|Default">
  <MonoDevelop.Ide.ItemProperties.CH1__Delegate PreferredExecutionTarget="MonoDevelop.Default" />
  <MonoDevelop.Ide.Workbench ActiveDocument="CH4_Action/Program.cs">
    <Files>
      <File FileName="CH4_Action/Program.cs" Line="81" Column="1" />
      <File FileName="CH2_Lambda/Program.cs" />
    </Files>
    <Pads>
      <Pad Id="ProjectPad">
        <State name="__root__">
          <Node name="DelegateNEvent" expanded="True">
            <Node name="CH2_Lambda" expanded="True" />
            <Node name="CH3_Event" expanded="True" />
            <Node name="CH4_Action" expanded="True">
              <Node name="Program.cs" selected="True" />
            </Node>
          </Node>
        </State>
      </Pad>
    </Pads>
  </MonoDevelop.Ide.Workbench>
  <MonoDevelop.Ide.ItemProperties.CH4__Action PreferredExecutionTarget="MonoDevelop.Default" />
  <MonoDevelop.Ide.DebuggingService.PinnedWatches />
  <DisabledProjects>
    <String>AboutLambda/CH2_Lambda.csproj</String>
    <String>AboutDelegate/CH1_Delegate.csproj</String>
  </DisabledProjects>
  <MonoDevelop.Ide.ItemProperties.CH2__Lambda PreferredExecutionTarget="MonoDevelop.Default" />
  <MonoDevelop.Ide.Workspace ActiveConfiguration="Debug" />
  <MonoDevelop.Ide.DebuggingService.Breakpoints>
    <BreakpointStore />
  </MonoDevelop.Ide.DebuggingService.Breakpoints>
  <MultiItemStartupConfigurations />
</Properties>